{
  "required": true,
  "package": "ua.zefir.zefiroptimizations.mixin",
  "compatibilityLevel": "JAVA_21",
  "mixins": [
    "AnimalEntityMixin",
    "EntityAccessor",
    "EntityMixin",
    "ItemEntityMixin",
    "LivingEntityAccessor",
    "LivingEntityMixin",
    "MobEntityAccessor",
    "MobEntityMixin",
    "ServerEntityManager$ListenerMixin",
    "ServerEntityManagerAccessor",
    "ServerEntityManagerInterfaceMixin",
    "ServerEntityManagerMixin",
    "ServerPlayerEntityMixin",
    "ServerWorldMixin",
    "WorldMixin"
  ],
  "injectors": {
    "defaultRequire": 1
	}
}